setup.py
bowshock/__init__.py
bowshock/apod.py
bowshock/asterank.py
bowshock/earth.py
bowshock/helioviewer.py
bowshock/helpers.py
bowshock/maas.py
bowshock/modis.py
bowshock/patents.py
bowshock/predictthesky.py
bowshock/skymorph.py
bowshock/star.py
bowshock/techport.py
bowshock/temperature_anomalies.py
bowshock.egg-info/PKG-INFO
bowshock.egg-info/SOURCES.txt
bowshock.egg-info/dependency_links.txt
bowshock.egg-info/requires.txt
bowshock.egg-info/top_level.txt