Metadata-Version: 1.1
Name: bowshock
Version: 0.0.2
Summary: An all-in-one library for NASA API's
Home-page: https://github.com/emirozer/bowshock
Author: Emir Ozer
Author-email: emirozer@yandex.com
License: UNKNOWN
Keywords: nasa api wrapper
Platform: UNKNOWN
Classifier: Development Status :: 4 - Beta
Classifier: Environment :: Console
Classifier: Intended Audience :: Developers
Classifier: Operating System :: OS Independent
Classifier: Programming Language :: Python
